{"nodes": [{"id": "node4", "label": "1", "attributes": {"label": 1, "name": "node4", "shape": "box", "fillcolor": "lightgray"}}, {"id": "node5", "label": "0", "attributes": {"label": 0, "name": "node5", "shape": "box", "fillcolor": "lightgray"}}, {"id": "x", "label": "x", "attributes": {"label": "x", "name": "x", "shape": "circle"}}, {"id": "y", "label": "y", "attributes": {"label": "y", "name": "y", "shape": "circle"}}, {"id": "z", "label": "z", "attributes": {"label": "z", "name": "z", "shape": "circle"}}], "edges": [{"source": "x", "target": "node4", "attributes": {"style": "dashed"}}, {"source": "x", "target": "y", "attributes": {"style": "solid"}}, {"source": "y", "target": "node5", "attributes": {"style": "dashed"}}, {"source": "y", "target": "z", "attributes": {"style": "solid"}}, {"source": "z", "target": "node4", "attributes": {"style": "dashed"}}, {"source": "z", "target": "node5", "attributes": {"style": "solid"}}]}
